README.md
setup.py
flasktool/__init__.py
flasktool/app.py
flasktool.egg-info/PKG-INFO
flasktool.egg-info/SOURCES.txt
flasktool.egg-info/dependency_links.txt
flasktool.egg-info/requires.txt
flasktool.egg-info/top_level.txt