Metadata-Version: 1.0
Name: flasktool
Version: 0.2.1
Summary: test pip upload
Home-page: https://github.com/fengmm521/pipProject
Author: zhangtianming
Author-email: 980152647@qq.com
License: MIT Licence
Keywords: pip,flasktool
Platform: any
